codebook_features/.DS_Store
codebook_features/__init__.py
codebook_features/code_search_cache.py
codebook_features/code_search_utils.py
codebook_features/config/__init__.py
codebook_features/config/fsm_main.yaml
codebook_features/config/main.yaml
codebook_features/config/test.yaml
codebook_features/config/test_fsm.yaml
codebook_features/config/test_tinystories.yaml
codebook_features/fsm.npy
codebook_features/fsm_utils.py
codebook_features/mod_model_classes.py
codebook_features/models.py
codebook_features/run_clm.py
codebook_features/tl_mods.py
codebook_features/train_codebook.py
codebook_features/train_fsm_model.py
codebook_features/trainer.py
codebook_features/utils.py
codebook_features/webapp/.streamlit/config.toml
codebook_features/webapp/Code_Browser.py
codebook_features/webapp/pages/Topic_Code_Browser.py
codebook_features/webapp/utils.py
codebook_features-0.1.2.dist-info/LICENSE
codebook_features-0.1.2.dist-info/METADATA
codebook_features-0.1.2.dist-info/WHEEL
codebook_features-0.1.2.dist-info/RECORD
