Metadata-Version: 2.1
Name: codebook-features
Version: 0.1.2
Summary: Sparse and discrete interpretability tool for neural networks
Home-page: https://huggingface.co/spaces/taufeeque/codebook-features
License: MIT
Keywords: codebook,features,transformers,language-models,interpretability
Author: Mohammad Taufeeque
Author-email: 9taufeeque9@gmail.com
Requires-Python: >3.9.7,<3.12
Classifier: License :: OSI Approved :: MIT License
Classifier: Programming Language :: Python :: 3
Classifier: Programming Language :: Python :: 3.10
Classifier: Programming Language :: Python :: 3.11
Requires-Dist: accelerate (>=0.21)
Requires-Dist: datasets (>=2.7.1)
Requires-Dist: evaluate (>=0.4.0)
Requires-Dist: hydra-core (>=1.3.0)
Requires-Dist: mypy (>=0.991)
Requires-Dist: plotly (>=5.17.0,<6.0.0)
Requires-Dist: ruff (>=0.0.200)
Requires-Dist: scikit-learn (>=1.2.0)
Requires-Dist: setuptools (>=68.2.2)
Requires-Dist: streamlit (>=1.26.0)
Requires-Dist: streamlit-extras (>=0.3.0)
Requires-Dist: termcolor (>=2.3.0)
Requires-Dist: torch (>=2.0.0)
Requires-Dist: transformer-lens (==1.7.0)
Requires-Dist: transformers (>=4.29)
Requires-Dist: wandb (>=0.14)
Requires-Dist: zstandard (>=0.19.0)
Project-URL: Repository, https://github.com/taufeeque9/codebook-features
